{
  "IND-PAK": {
    "00_overview": {
      "summary": "India-Pakistan relations are marked by historical animosity stemming from Partition (1947), territorial disputes (Kashmir), and multiple wars (1947, 1965, 1971, 1999). Diplomatic ties remain minimal with frequent border tensions.",
      "key_facts": [
        "Nuclear-armed neighbors with 3,323 km shared border",
        "Four major wars since independence (1947, 1965, 1971, 1999)",
        "Kashmir dispute remains core issue since 1947",
        "Bilateral trade suspended since August 2019",
        "No official dialogue mechanism active as of 2025"
      ],
      "relationship_emoji": "⚠️",
      "strength_score": 25,
      "statistics": {
        "border_length": "3,323 km",
        "trade_volume_2024": "$0.33 billion (informal)",
        "diplomatic_missions": "2 (minimal staff)",
        "visa_issuance_2024": "~12,000 (religious/medical)"
      },
      "visualizations": [
        {
          "type": "d3",
          "chart_type": "radar",
          "title": "Relationship Health Indicators",
          "data": {
            "labels": ["Political", "Economic", "Defense", "Cultural", "Diplomatic", "People-to-People"],
            "country1": "India",
            "country2": "Pakistan",
            "country1_values": [15, 5, 10, 30, 20, 25],
            "country2_values": [15, 5, 10, 30, 20, 25]
          }
        }
      ]
    },
    
    "01_historical_background": {
      "timeline": [
        {
          "year": "1947",
          "event": "Partition of British India creates India and Pakistan; First Kashmir War begins",
          "impact": "negative",
          "source": "Ministry of External Affairs India, Government of Pakistan Archives"
        },
        {
          "year": "1965",
          "event": "Second India-Pakistan War over Kashmir",
          "impact": "negative",
          "source": "UN Security Council Resolution 211"
        },
        {
          "year": "1971",
          "event": "Bangladesh Liberation War; Pakistan loses East Pakistan",
          "impact": "negative",
          "source": "Hamoodur Rahman Commission Report, MEA India"
        },
        {
          "year": "1999",
          "event": "Kargil War in Kashmir region",
          "impact": "negative",
          "source": "Kargil Review Committee Report, Pakistan Foreign Office"
        },
        {
          "year": "2001",
          "event": "Indian Parliament attack; military standoff (Operation Parakram)",
          "impact": "negative",
          "source": "Ministry of Home Affairs India"
        },
        {
          "year": "2008",
          "event": "Mumbai terror attacks (26/11); composite dialogue suspended",
          "impact": "negative",
          "source": "National Investigation Agency India, UN Security Council"
        },
        {
          "year": "2019",
          "event": "Pulwama attack; Balakot airstrikes; Article 370 revocation; trade suspended",
          "impact": "negative",
          "source": "MEA India, Pakistan Foreign Office, UN reports"
        }
      ],
      "visualizations": [
        {
          "type": "d3",
          "chart_type": "timeline",
          "title": "India-Pakistan Conflict Timeline",
          "data": {
            "events": [
              {"year": "1947", "event": "Partition & 1st War", "impact": "negative"},
              {"year": "1965", "event": "2nd Kashmir War", "impact": "negative"},
              {"year": "1971", "event": "Bangladesh War", "impact": "negative"},
              {"year": "1999", "event": "Kargil War", "impact": "negative"},
              {"year": "2001", "event": "Parliament Attack", "impact": "negative"},
              {"year": "2008", "event": "Mumbai Attacks", "impact": "negative"},
              {"year": "2019", "event": "Pulwama-Balakot", "impact": "negative"}
            ]
          }
        }
      ]
    },
    
    "02_bilateral_ties": {
      "diplomatic_missions": {
        "india_in_pakistan": "High Commission in Islamabad (minimal staff since 2019)",
        "pakistan_in_india": "High Commission in New Delhi (minimal staff since 2019)"
      },
      "ambassadors": {
        "india": "Charge d'Affaires (no High Commissioner since 2019)",
        "pakistan": "Charge d'Affaires (no High Commissioner since 2019)"
      },
      "state_visits": [
        {
          "date": "2015-12-25",
          "description": "PM Narendra Modi surprise visit to Lahore",
          "source": "MEA India Press Release"
        },
        {
          "date": "2016-01-02",
          "description": "Pathankot airbase terror attack; dialogue suspended",
          "source": "National Investigation Agency India"
        }
      ],
      "current_status": "Relations at historic low; no formal dialogue since 2019"
    },
    
    "03_agreements_treaties": {
      "treaties": [
        {
          "name": "Indus Waters Treaty",
          "year": "1960",
          "status": "Active (despite conflicts)",
          "significance": "Water-sharing agreement; mediated by World Bank; survived all wars",
          "source": "World Bank, MEA India, Pakistan Water & Power Development Authority"
        },
        {
          "name": "Simla Agreement",
          "year": "1972",
          "status": "Active",
          "significance": "Post-1971 war settlement; LoC established in Kashmir",
          "source": "MEA India, Pakistan Foreign Office"
        },
        {
          "name": "Lahore Declaration",
          "year": "1999",
          "status": "Ineffective",
          "significance": "Peace commitment; violated same year by Kargil War",
          "source": "MEA India Archives"
        }
      ]
    },
    
    "04_political_relations": {
      "dialogues": [],
      "disputes": [
        "Kashmir territorial dispute (since 1947)",
        "Cross-border terrorism accusations",
        "Water-sharing tensions (despite Indus Treaty)",
        "Sir Creek maritime boundary dispute",
        "Siachen Glacier territorial claims"
      ],
      "convergence": [
        "Both members of SAARC (South Asian Association for Regional Cooperation)",
        "Both members of Shanghai Cooperation Organisation (SCO)"
      ]
    },
    
    "05_economic_trade": {
      "trade_volume": {
        "total": "$0.33 billion (2024, unofficial via third countries)",
        "official_status": "All bilateral trade suspended since August 2019",
        "source": "UN Comtrade, Reserve Bank of India, State Bank of Pakistan"
      },
      "top_exports": [
        "India to Pakistan (pre-2019): Organic chemicals, cotton, petroleum products",
        "Current: All formal trade halted"
      ],
      "top_imports": [
        "Pakistan to India (pre-2019): Cement, fresh fruits, leather",
        "Current: All formal trade halted"
      ],
      "trade_potential": {
        "estimate": "$40 billion annually (if normalized)",
        "source": "World Bank South Asia Economic Focus 2024"
      },
      "visualizations": [
        {
          "type": "chartjs",
          "chart_type": "line",
          "title": "India-Pakistan Trade Volume (2010-2024)",
          "data": {
            "years": ["2010", "2012", "2014", "2016", "2018", "2019", "2020", "2022", "2024"],
            "values": [1.6, 2.1, 2.4, 2.6, 2.3, 2.0, 0.4, 0.35, 0.33],
            "metric": "Trade Volume ($ Billion)"
          }
        }
      ]
    },
    
    "06_defense_security": {
      "military_comparison": {
        "india_active_troops": "1,450,000 (SIPRI 2026)",
        "pakistan_active_troops": "654,000 (SIPRI 2026)",
        "india_defense_budget": "$81.4 billion (2025-26)",
        "pakistan_defense_budget": "$10.3 billion (2025-26)",
        "nuclear_warheads_india": "164 (est. 2025, Federation of American Scientists)",
        "nuclear_warheads_pakistan": "170 (est. 2025, FAS)"
      },
      "cooperation": [],
      "border_status": "3,323 km Line of Control (LoC) in Kashmir; frequent ceasefire violations",
      "conflicts": [
        "1947-48 Kashmir War",
        "1965 War",
        "1971 Bangladesh Liberation War",
        "1999 Kargil War",
        "2001-02 Military Standoff",
        "2019 Balakot Airstrikes"
      ],
      "visualizations": [
        {
          "type": "chartjs",
          "chart_type": "bar",
          "title": "Military Strength Comparison (2026)",
          "data": {
            "labels": ["Active Troops (thousands)", "Defense Budget ($ billions)", "Nuclear Warheads"],
            "country1": "India",
            "country2": "Pakistan",
            "country1_values": [1450, 81.4, 164],
            "country2_values": [654, 10.3, 170]
          }
        }
      ]
    },
    
    "07_people_to_people": {
      "visa_regime": "Highly restrictive; only city-specific visas for religious/medical purposes",
      "diaspora": "Approx 1.5 million Indian diaspora in Pakistan (1947 Partition-era); 1.2 million Pakistani diaspora in India",
      "students": "No student exchange programs; educational visas rarely granted",
      "tourism": "Tourism visas virtually non-existent; only religious pilgrims (Kartarpur Corridor for Sikhs)",
      "cultural_exchanges": "Minimal; some artists/cricketers occasionally visit"
    },
    
    "08_connectivity": {
      "air": "No direct flights since 2019; all airspace closed to each other's airlines",
      "rail": "Samjhauta Express and Thar Express suspended since 2019",
      "road": "Wagah-Attari border crossing open for trade (suspended 2019); only pedestrian for Kartarpur",
      "sea": "No direct shipping routes",
      "digital": "Internet services blocked near border areas during tensions"
    },
    
    "09_multilateral_forums": {
      "common_organizations": [
        "United Nations",
        "South Asian Association for Regional Cooperation (SAARC)",
        "Shanghai Cooperation Organisation (SCO)",
        "Commonwealth of Nations"
      ],
      "voting_alignment": "Low; often vote oppositely on Kashmir-related UN resolutions",
      "saarc_status": "Stalled since 2016; India boycotted 2016 summit in Islamabad"
    },
    
    "10_sectoral_cooperation": {
      "energy": "No cooperation; India blocked Pakistan's participation in TAPI gas pipeline",
      "climate": "No joint initiatives despite shared climate vulnerabilities (Himalayan glaciers, Indus basin)",
      "science": "No scientific collaboration",
      "space": "No cooperation",
      "health": "Emergency medical visas occasionally granted; no institutional cooperation",
      "agriculture": "No cooperation despite shared agricultural challenges (water, pests)"
    },
    
    "11_influence_third_parties": {
      "influencers": [
        "United States (major arms supplier to Pakistan; strategic partner to India)",
        "China (all-weather ally of Pakistan; border tensions with India)",
        "Saudi Arabia (close to Pakistan; growing ties with India)",
        "UAE (close to both; mediation attempts)"
      ],
      "proxies": [
        "Afghanistan (Pakistan-backed Taliban vs India-backed previous govt)",
        "Bangladesh (India's ally; Pakistan seeks influence)",
        "Nepal (both compete for influence)"
      ],
      "visualizations": [
        {
          "type": "d3",
          "chart_type": "network",
          "title": "Third-Party Influence Network",
          "data": {
            "nodes": [
              {"id": "IND", "name": "India", "type": "primary"},
              {"id": "PAK", "name": "Pakistan", "type": "primary"},
              {"id": "USA", "name": "USA", "type": "influencer"},
              {"id": "CHN", "name": "China", "type": "influencer"},
              {"id": "SAU", "name": "Saudi Arabia", "type": "influencer"},
              {"id": "AFG", "name": "Afghanistan", "type": "proxy"}
            ],
            "links": [
              {"source": "USA", "target": "IND", "value": 8},
              {"source": "USA", "target": "PAK", "value": 6},
              {"source": "CHN", "target": "PAK", "value": 10},
              {"source": "CHN", "target": "IND", "value": 3},
              {"source": "SAU", "target": "PAK", "value": 9},
              {"source": "SAU", "target": "IND", "value": 7}
            ]
          }
        }
      ]
    },
    
    "12_areas_of_concern": {
      "disputes": [
        {
          "title": "Kashmir Territorial Dispute",
          "description": "Core issue since 1947; India controls Jammu & Kashmir (revoked autonomy 2019), Pakistan controls Azad Kashmir & Gilgit-Baltistan, China controls Aksai Chin",
          "source": "UN Security Council Resolutions 47 (1948), MEA India, Pakistan Foreign Office"
        },
        {
          "title": "Cross-Border Terrorism",
          "description": "India accuses Pakistan of sponsoring terror groups (Lashkar-e-Taiba, Jaish-e-Mohammed); Pakistan denies allegations",
          "source": "Financial Action Task Force (FATF) reports, US State Dept terrorism reports"
        },
        {
          "title": "Water Disputes",
          "description": "India building dams on western rivers (Indus, Jhelum, Chenab); Pakistan raises objections despite Indus Treaty",
          "source": "World Bank Indus Waters Treaty monitoring"
        }
      ]
    },
    
    "13_future_outlook": {
      "short_term": [
        "Status quo likely to continue; no dialogue expected in 2026-27",
        "Border tensions may escalate during election periods",
        "Backchannel diplomacy possible via UAE/Saudi mediation"
      ],
      "medium_term": [
        "Potential dialogue if leadership changes in either country (2028-30)",
        "Economic pressures may push limited trade resumption",
        "Climate crisis (water scarcity) could force cooperation"
      ],
      "long_term": [
        "Kashmir issue unlikely to resolve without major geopolitical shift",
        "Generational change may reduce Partition-era animosity (post-2035)",
        "China-US dynamics could realign India-Pakistan calculations"
      ],
      "wildcards": [
        "Another major terror attack triggering military conflict",
        "Nuclear flashpoint scenario (low probability, catastrophic impact)",
        "Internal instability in Pakistan forcing policy shifts",
        "SAARC revival under new framework"
      ]
    },
    
    "14_imaginary_peace_scenario": {
      "vision": "A peaceful, cooperative India-Pakistan relationship would create the world's largest integrated economy (1.6 billion people), unlock $40B annual trade, save $23B/year in defense spending, and transform South Asia into a global growth engine.",
      "peace_potential_score": 85,
      "quantified_benefits": {
        "trade_potential": "$40 billion/year",
        "defense_savings": "$23 billion/year (combined)",
        "gdp_boost": "+2.5% for Pakistan, +1.2% for India",
        "tourism_revenue": "$8 billion/year",
        "cross_border_investment": "$15 billion (5 years)"
      },
      "roadmap": [
        {
          "phase": "1. Confidence Building (Year 1-2)",
          "steps": [
            "Restore diplomatic staff to full strength",
            "Resume Samjhauta Express and bus services",
            "Open 5 additional border crossings for trade",
            "Restart cricket diplomacy (bilateral series)",
            "Joint water management commission under Indus Treaty"
          ]
        },
        {
          "phase": "2. Economic Integration (Year 3-5)",
          "steps": [
            "Grant Most Favored Nation (MFN) status mutually",
            "Operationalize SAARC motor vehicle agreement",
            "Create India-Pakistan Business Council",
            "Launch Lahore-Amritsar-Delhi high-speed rail",
            "Open skies agreement for direct flights"
          ]
        },
        {
          "phase": "3. Kashmir Resolution (Year 6-10)",
          "steps": [
            "LoC declared permanent soft border (open for trade/travel)",
            "Joint administration of disputed territories (like EU Schengen)",
            "UN-mediated plebiscite in select regions",
            "Demilitarization roadmap with international monitoring",
            "Shared sovereignty model inspired by Good Friday Agreement"
          ]
        }
      ],
      "prerequisites": [
        "Sustained political will in both capitals",
        "Zero-tolerance for cross-border terrorism (Pakistan action on militant groups)",
        "India's acceptance of third-party mediation on Kashmir",
        "International support (US, China, UAE guarantors)"
      ],
      "inspirational_quote": "If Europe can unify after World Wars, India and Pakistan can reconcile after Partition. Peace is not just the absence of war, but the presence of prosperity for 1.6 billion people yearning for it. - Adapted from regional peace advocates",
      "visualizations": [
        {
          "type": "d3",
          "chart_type": "timeline",
          "title": "10-Year Peace Roadmap",
          "data": {
            "events": [
              {"year": "Year 1", "event": "Restore Diplomacy", "impact": "positive"},
              {"year": "Year 2", "event": "Resume Transport Links", "impact": "positive"},
              {"year": "Year 3", "event": "MFN Status Granted", "impact": "positive"},
              {"year": "Year 5", "event": "HSR Operational", "impact": "positive"},
              {"year": "Year 7", "event": "Soft Border Kashmir", "impact": "positive"},
              {"year": "Year 10", "event": "Full Normalization", "impact": "positive"}
            ]
          }
        }
      ]
    },
    
    "15_us_intervention_analysis": {
      "interventions": [
        {
          "title": "Afghanistan War (2001-2021)",
          "period": "2001-2021",
          "description": "US invasion of Afghanistan post-9/11 forced Pakistan to become frontline state against Taliban (despite Pakistan's covert support). India supported Northern Alliance. US aid to Pakistan: $33 billion (2001-2020). Created India-Pakistan proxy war in Afghanistan.",
          "source": "US Special Inspector General for Afghanistan Reconstruction (SIGAR), Congressional Research Service"
        },
        {
          "title": "F-16 Sales to Pakistan",
          "period": "1980s-2010s",
          "description": "US supplied Pakistan with F-16 fighter jets despite India's objections. Latest: 8 F-16s approved in 2016 ($699M). Shifted balance of air power in South Asia.",
          "source": "US Defense Security Cooperation Agency, Stockholm International Peace Research Institute"
        }
      ],
      "actual_outcomes": [
        "Pakistan became nuclear power with US tacit approval (1998)",
        "Kashmir militancy intensified post-Afghan Jihad (1990s-2000s)",
        "India-Pakistan wars averted by US mediation (1999 Kargil, 2001-02 standoff)",
        "Afghanistan remains unstable; Taliban rule since 2021"
      ],
      "alternative_scenario_without_us": [
        "Scenario A: No Afghan War → No Taliban rise → Pakistan not destabilized by militancy",
        "Scenario B: India-Pakistan left to resolve Kashmir bilaterally → Potential SCO mediation",
        "Scenario C: No US arms to Pakistan → India's conventional military superiority leads to earlier resolution",
        "Quantified: US aid ($33B to Pakistan) could have funded 5,000 km of cross-border rail if spent on peace"
      ],
      "regional_autonomy": {
        "sco_mediation_potential": "Shanghai Cooperation Organisation (Russia-China led) could mediate Kashmir if US withdrew; more acceptable to Pakistan than Western mediation",
        "saarc_revival": "Without US influence, SAARC could function as EU-like framework with joint Kashmir administration"
      },
      "visualizations": [
        {
          "type": "d3",
          "chart_type": "timeline",
          "title": "US Interventions Impact Timeline",
          "data": {
            "events": [
              {"year": "1979", "event": "US backs Afghan Mujahideen", "impact": "negative"},
              {"year": "1998", "event": "Pakistan nuclear tests (US sanctions)", "impact": "mixed"},
              {"year": "2001", "event": "Afghanistan War begins", "impact": "negative"},
              {"year": "2011", "event": "Bin Laden raid in Pakistan", "impact": "negative"},
              {"year": "2016", "event": "F-16 sale to Pakistan", "impact": "negative"},
              {"year": "2021", "event": "US withdraws from Afghanistan", "impact": "mixed"}
            ]
          }
        }
      ]
    }
  }
}
